{
  "interactionModel": {
    "languageModel": {
      "invocationName": "pet match",
      "intents": [
        {
          "name": "AMAZON.CancelIntent",
          "samples": []
        },
        {
          "name": "AMAZON.HelpIntent",
          "samples": []
        },
        {
          "name": "AMAZON.StopIntent",
          "samples": []
        },
        {
          "name": "HelloWorldIntent",
          "slots": [],
          "samples": [
            "hello",
            "how are you",
            "say hi world",
            "say hi",
            "hi",
            "say hello world",
            "say hello"
          ]
        },
        {
          "name": "AMAZON.NavigateHomeIntent",
          "samples": []
        },
        {
          "name": "AMAZON.FallbackIntent",
          "samples": []
        }
      ],
      "types": [
        {
          "name": "Fruit",
          "values": [
            {
              "name": {
                "value": "red"
              }
            },
            {
              "name": {
                "value": "blue"
              }
            },
            {
              "name": {
                "value": "yellow"
              }
            },
            {
              "name": {
                "value": "fakecheck",
                "synonyms": ["fake check", "check bounced", "bounced check", "bad check"]
              }
            }
          ]
        },
        {
          "name": "stringLiteral",
          "values": [
            {
              "name": {
                "value": "dummy value: literal API return entity"
              }
            }
          ]
        }
      ]
    }
  }
}
